FPGA_DLD_LAB/lab3_dff_srlatch/part4/neg_edge_flip_flop.sv
module neg_edge_flip_flop(
  input wire Clk,
  input wire D,
  output reg Qn
);

  // Negative-edge triggered D flip-flop
  always @(negedge Clk) begin
    Qn <= D;
  end

endmodule

FPGA_DLD_LAB/lab3_dff_srlatch/part4/pos_edge_flip_flop.sv
module pos_edge_flip_flop(
  input wire Clk,
  input wire D,
  output reg Qp
);

  // Positive-edge triggered D flip-flop
  always @(posedge Clk) begin
    Qp <= D;
  end

endmodule

FPGA_DLD_LAB/lab3_dff_srlatch/part4/gated_d_latch.sv
module gated_d_latch(
  input wire Clk,
  input wire D,
  output reg Qd
);

  // Gated D latch
 always @(Clk,D)
  begin
   if (Clk)
    Qd = D;
  end
  
endmodule

FPGA_DLD_LAB/lab3_dff_srlatch/part4/part4.sv
module part4(
  input wire Clk,
  input wire D,
  output reg Qd,
  output reg Qp,
  output reg Qn
);

  // Instantiate modules
  gated_d_latch uut_gated_d_latch (
    .Clk(Clk),
    .D(D),
    .Qd(Qd)
  );

  pos_edge_flip_flop uut_pos_edge_flip_flop (
    .Clk(Clk),
    .D(D),
    .Qp(Qp)
  );

  neg_edge_flip_flop uut_neg_edge_flip_flop (
    .Clk(Clk),
    .D(D),
    .Qn(Qn)
  );

endmodule

FPGA_DLD_LAB/lab3_dff_srlatch/part4/part4_tb.sv
// Code your testbench here
// or browse Examples

module part4_tb;

  // Declare signals

logic clk, d, qd,qp,qn;
initial
begin
d = 0; #2.5;
d = 1; #2.5;
d = 0; #1;
d = 1; #1.5;
d = 0; #1.5;
d = 1; #1;
d = 0; #0.5;
d = 1; #1;
d = 0; #1.5;
d = 1; #1;
d = 0; #1.5;  
d = 1; #1.5;
d= 0; #0.5;
end
always
begin
clk =0; #5;
clk =1; #5;
end

   // Instantiate the module
  part4 dut(
    .Clk(clk),
    .D(d),
    .Qd(qd),
    .Qp(qp),
    .Qn(qn)
  );
  
   initial begin 
      $dumpfile("dump.vcd");
      $dumpvars(0);
      #25;
      $finish();
    end

endmodule

FPGA_DLD_LAB/lab3_dff_srlatch/part4/simulation/modelsim/dump.vcd
$date
	Sun Dec 31 18:01:49 2023
$end
$version
	ModelSim Version 10.5b
$end
$timescale
	1ps
$end

$scope module part4_tb $end
$var reg 1 ! clk $end
$var reg 1 " d $end
$var reg 1 # qd $end
$var reg 1 $ qp $end
$var reg 1 % qn $end

$scope module dut $end
$var wire 1 & Clk $end
$var wire 1 ' D $end
$var reg 1 ( Qd $end
$var reg 1 ) Qp $end
$var reg 1 * Qn $end

$scope module uut_gated_d_latch $end
$var wire 1 & Clk $end
$var wire 1 ' D $end
$var reg 1 + Qd $end
$upscope $end

$scope module uut_pos_edge_flip_flop $end
$var wire 1 & Clk $end
$var wire 1 ' D $end
$var reg 1 , Qp $end
$upscope $end

$scope module uut_neg_edge_flip_flop $end
$var wire 1 & Clk $end
$var wire 1 ' D $end
$var reg 1 - Qn $end
$upscope $end
$upscope $end
$upscope $end
$enddefinitions $end
#0
$dumpvars
0!
0"
x#
x$
0%
x(
x)
0*
x+
x,
0-
0&
0'
$end
#3
1"
1'
#5
1!
1&
1+
1(
1#
1,
1)
1$
#6
0"
0'
0+
0(
0#
#7
1"
1'
1+
1(
1#
#9
0"
0'
0+
0(
0#
#10
0!
0&
#11
1"
1'
#12
0"
0'
#13
1"
1'
#14
0"
0'
#15
1!
1&
0,
0)
0$
#16
1"
1'
1+
1(
1#
#17
0"
0'
0+
0(
0#
#19
1"
1'
1+
1(
1#
#20
0!
0&
1-
1*
1%
#21
0"
0'
